MANIFEST.in
README.rst
requirements.txt
setup.py
pyromarc/__init__.py
pyromarc/format.py
pyromarc/mir.py
pyromarc/utils.py
pyromarc.egg-info/PKG-INFO
pyromarc.egg-info/SOURCES.txt
pyromarc.egg-info/dependency_links.txt
pyromarc.egg-info/requires.txt
pyromarc.egg-info/top_level.txt