Metadata-Version: 1.1
Name: pyromarc
Version: 0.1
Summary: Python implementation of MARC:MIR
Home-page: https://github.com/agrausem/pyromarc
Author: Arnaud Grausem
Author-email: arnaud.grausem@gmail.com
License: PSF
Download-URL: http://pypi.python.org/pypi/pyromarc
Keywords: MARC,ISO2709,msgpack,MIR,MARC:MIR
Platform: UNKNOWN
Classifier: Development Status :: 3 - Alpha
Classifier: Environment :: Console
Classifier: Intended Audience :: Developers
Classifier: License :: OSI Approved :: BSD License
Classifier: Operating System :: OS Independent
Classifier: Programming Language :: Python :: 3.2
Classifier: Topic :: Text Processing
Classifier: Topic :: Software Development :: Libraries
